ftrack_framework_qt/__init__.py
ftrack_framework_qt/dialogs/__init__.py
ftrack_framework_qt/dialogs/base_context_dialog.py
ftrack_framework_qt/dialogs/base_dialog.py
ftrack_framework_qt/widgets/__init__.py
ftrack_framework_qt/widgets/base_widget.py
ftrack_framework_qt-2.2.0.dist-info/LICENSE.txt
ftrack_framework_qt-2.2.0.dist-info/METADATA
ftrack_framework_qt-2.2.0.dist-info/WHEEL
ftrack_framework_qt-2.2.0.dist-info/RECORD
